virtualmicroscope/__init__.py
virtualmicroscope/urls.py
virtualmicroscope/views.py
virtualmicroscope/templates/virtualmicroscope/start.html
omero_virtual_microscope-1.2.0.dist-info/LICENSE
omero_virtual_microscope-1.2.0.dist-info/METADATA
omero_virtual_microscope-1.2.0.dist-info/WHEEL
omero_virtual_microscope-1.2.0.dist-info/top_level.txt
omero_virtual_microscope-1.2.0.dist-info/RECORD
