Metadata-Version: 2.1
Name: omero-virtual-microscope
Version: 1.2.0
Summary: Virtual Microscope OMERO.web extension application
Home-page: https://github.com/ome/virtual-microscope
Author: The Open Microscopy Team
Author-email: ome-devel@lists.openmicroscopy.org.uk
License: AGPL-3.0
Download-URL: https://github.com/ome/virtual-microscope/archive/v1.2.0.zip
Keywords: OMERO.web,plugin
Platform: UNKNOWN
Classifier: Environment :: Web Environment
Classifier: Framework :: Django
Classifier: Intended Audience :: Developers
Classifier: Natural Language :: English
Classifier: Operating System :: OS Independent
Classifier: Programming Language :: Python :: 3
Classifier: Topic :: Internet :: WWW/HTTP
Classifier: Topic :: Internet :: WWW/HTTP :: Dynamic Content
Requires-Python: >=3
License-File: LICENSE
Requires-Dist: omero-web (>=5.6.0)
